setup.py
code/__init__.py
hamed_hack.egg-info/PKG-INFO
hamed_hack.egg-info/SOURCES.txt
hamed_hack.egg-info/dependency_links.txt
hamed_hack.egg-info/top_level.txt